{
    "AX": {
        "error": 1e-20,
        "fit": "default",
        "references": [],
        "value": 1.0
    },
    "H1": {
        "error": 0.000126839861749943,
        "fit": "Bracketing Interpolate",
        "references": [
            {
                "exclude": "ok",
                "record_id": "c-03-F-503",
                "uuid": "9718b497-3f5d-4bd2-ac4a-e1c72f06ed65"
            },
            {
                "exclude": "ok",
                "record_id": "c-03-F-504",
                "uuid": "e9a58989-ee3b-4e4c-99e2-4aed201404e2"
            },
            {
                "exclude": "ok",
                "record_id": "c-03-F-505",
                "uuid": "0f96791b-38cb-4811-91a7-2b4acd22258e"
            },
            {
                "exclude": "ok",
                "record_id": "c-03-F-506",
                "uuid": "defc0be4-a21d-4536-b85f-2a90331e5cca"
            },
            {
                "exclude": "ok",
                "record_id": "c-03-F-507",
                "uuid": "2f8b3d72-5683-465f-babe-d79c312d2b7d"
            },
            {
                "exclude": "ok",
                "record_id": "c-03-F-508",
                "uuid": "9fece102-04af-4e2d-bbc5-ee955400962d"
            },
            {
                "exclude": "ok",
                "record_id": "c-03-F-509",
                "uuid": "0746556e-22e0-4854-9c63-bd33e2b28056"
            },
            {
                "exclude": "ok",
                "record_id": "c-03-F-510",
                "uuid": "71026e64-ce37-47fb-91a3-e266ec645a3b"
            }
        ],
        "reviewed": true,
        "value": 1.0030638730851984
    },
    "H2": {
        "error": 1e-20,
        "fit": "default",
        "references": [],
        "value": 1.0
    },
    "L1": {
        "error": 1e-20,
        "fit": "default",
        "references": [],
        "value": 1.0
    },
    "L2(CDD)": {
        "error": 0.0013443435589527274,
        "fit": "Weighted Mean",
        "references": [
            {
                "exclude": "ok",
                "record_id": "a-02-F-2581",
                "uuid": "1df8eaed-c01b-4926-9b94-0792cce1da8b"
            },
            {
                "exclude": "ok",
                "record_id": "a-02-F-2582",
                "uuid": "1b0a3e37-0587-4c5f-a536-fd0b23a04f05"
            },
            {
                "exclude": "ok",
                "record_id": "a-02-F-2583",
                "uuid": "5251f8a8-5299-493c-ab76-a781f638c166"
            },
            {
                "exclude": "ok",
                "record_id": "a-02-F-2584",
                "uuid": "ad962130-6175-42e5-b882-2d14d26be1a0"
            },
            {
                "exclude": "ok",
                "record_id": "a-02-F-2585",
                "uuid": "d0d03565-c69f-48ec-886e-e391a09bbc29"
            },
            {
                "exclude": "ok",
                "record_id": "a-02-F-2586",
                "uuid": "71514a52-f7cf-4333-ad15-b0299dd62755"
            },
            {
                "exclude": "ok",
                "record_id": "a-02-F-2587",
                "uuid": "e62c5c10-046b-46a0-9e61-92677556ae81"
            },
            {
                "exclude": "ok",
                "record_id": "a-02-F-2588",
                "uuid": "f6e8116b-80c9-432c-af09-188c269501b6"
            }
        ],
        "reviewed": true,
        "value": 1.0303308642365454
    }
}